resume_md/__init__.py
resume_md/component_factory.py
resume_md/components.py
resume_md/main.py
resume_md/renderer.py
resume_md/template.html
resume_md/tokenizer.py
resume_md-1.3.0.dist-info/METADATA
resume_md-1.3.0.dist-info/WHEEL
resume_md-1.3.0.dist-info/entry_points.txt
resume_md-1.3.0.dist-info/top_level.txt
resume_md-1.3.0.dist-info/RECORD
