Metadata-Version: 2.4
Name: resume-md
Version: 1.3.0
Summary: Resume markdown to print ready HTML for email or web
Author-email: Sam Cullin <sam@miplace.com>
License-Expression: MIT
Project-URL: Homepage, https://github.com/SamCullin/resume-md
Project-URL: Bug Tracker, https://github.com/SamCullin/resume-md/issues
Project-URL: Source, https://github.com/SamCullin/resume-md
Keywords: resume,cv,markdown,pdf,print,html,tailwind,generator,web,email,ats
Classifier: Development Status :: 4 - Beta
Classifier: Environment :: Console
Classifier: Intended Audience :: Developers
Classifier: Programming Language :: Python :: 3
Classifier: Programming Language :: Python :: 3.9
Classifier: Programming Language :: Python :: 3.10
Classifier: Programming Language :: Python :: 3.11
Classifier: Programming Language :: Python :: 3.12
Classifier: Topic :: Text Processing :: Markup
Classifier: Topic :: Office/Business
Requires-Python: >=3.9
Requires-Dist: importlib_resources>=1.4.0; python_version < "3.9"
Provides-Extra: dev
Requires-Dist: autoflake>=2.3.1; extra == "dev"
Requires-Dist: black>=25.1.0; extra == "dev"
Requires-Dist: build>=1.2.2.post1; extra == "dev"
Requires-Dist: flake8>=7.2.0; extra == "dev"
Requires-Dist: isort>=6.0.1; extra == "dev"
Requires-Dist: pre-commit>=3.6.0; extra == "dev"
Requires-Dist: pytest>=8.3.5; extra == "dev"
Requires-Dist: python-semantic-release>=9.21.1; extra == "dev"
Requires-Dist: sigstore>=0.8.3; extra == "dev"
Provides-Extra: test
Requires-Dist: pytest>=7.0.0; extra == "test"
Requires-Dist: pytest-cov>=4.0.0; extra == "test"
